hyranote/__init__.py
hyranote/asciidoc_visitor.py
hyranote/cli.py
hyranote/cmd_dump.py
hyranote/cmd_generate.py
hyranote/cmd_simple.py
hyranote/hutil.py
hyranote/hyranote.py
hyranote/logging.py
hyranote/visitor.py
hyranote-0.3.0.dist-info/LICENSE
hyranote-0.3.0.dist-info/METADATA
hyranote-0.3.0.dist-info/WHEEL
hyranote-0.3.0.dist-info/entry_points.txt
hyranote-0.3.0.dist-info/top_level.txt
hyranote-0.3.0.dist-info/RECORD
