Metadata-Version: 2.1
Name: hyranote
Version: 0.3.0
Summary: Transform mindnode file to weekly notes
Home-page: http://github.com/huuhoa/hyranote
Author: Huu Hoa NGUYEN
Author-email: huuhoa@gmail.com
License: MIT License
Platform: UNKNOWN
Classifier: Programming Language :: Python :: 3
Classifier: License :: OSI Approved :: MIT License
Classifier: Operating System :: OS Independent
License-File: LICENSE
Requires-Dist: beautifulsoup4 (==4.9.1)
